  {
    "one" : [
      {"id": 1, "largetext": "Is this colour combination accessible?", "color": "8B2D77", "backgroundcolor": "77D58B"}
    ],
    "two" : [
      {"id": 3, "largetext": "Is this colour combination accessible?", "color": "4BAB00", "backgroundcolor": "FFE7B8"}
    ],
    "three" : [
      {"id": 2, "largetext": "Is this colour combination accessible?", "color": "FF0000", "backgroundcolor": "03009C"}
    ],
    "four" : [
      {"id": 4, "largetext": "Is this colour combination accessible?", "color": "FFFFFF", "backgroundcolor": "7FC3D2"}
    ],
    "five" : [
      {"id": 5, "largetext": "Is this colour combination accessible?", "color": "FAFF00", "backgroundcolor": "9F0099"}
    ],
    "six" : [
      {"id": 6, "largetext": "Is this colour combination accessible?", "color": "000000", "backgroundcolor": "008A69"}
    ],
    "seven" : [
      {"id": 7, "largetext": "Is this colour combination accessible?", "color": "FF7A00", "backgroundcolor": "FBFF40"}
    ],
    "eight" : [
      {"id": 8, "largetext": "Is this colour combination accessible?", "color": "00E0FF", "backgroundcolor": "890000"}
    ],
    "nine" : [
      {"id": 9, "largetext": "Is this colour combination accessible?", "color": "FF008A", "backgroundcolor": "FFA471"}
    ],
    "ten" : [
      {"id": 10, "largetext": "Is this colour combination accessible?", "color": "BED5D8", "backgroundcolor": "464F7C"}
    ]
  }